{
  "id": 4,
  "name": "第１章（METAL）",
  "events": [
    {
      "id": 150,
      "date": "2016-07-10",
      "title": "巣鴨獅子王",
      "form": "BAND"
    },
    {
      "id": 149,
      "date": "2016-08-27",
      "title": "渋谷Guilty",
      "form": "BAND"
    },
    {
      "id": 139,
      "date": "2016-11-23",
      "title": "LIVE AT 目黒鹿鳴館",
      "form": "BAND"
    },
    {
      "id": 138,
      "date": "2017-01-08",
      "title": "LEGEND \"2017\"",
      "form": "BAND"
    },
    {
      "id": 137,
      "date": "2017-02-26",
      "title": "天下一メタル武道お茶会",
      "form": "BAND"
    },
    {
      "id": 136,
      "date": "2017-04-22",
      "title": "きつね楽員 × DIZZYMETAL",
      "form": "BAND"
    },
    {
      "id": 148,
      "date": "2017-05-21",
      "title": "TRIBUTE BAND FESTIVAL 2017 @ CLUB CITTA'",
      "form": "BAND"
    },
    {
      "id": 147,
      "date": "2017-06-11",
      "title": "FOXY GIRLS PARTY",
      "form": "BAND"
    },
    {
      "id": 151,
      "date": "2017-08-26",
      "title": "立川BABEL",
      "form": "BAND"
    },
    {
      "id": 146,
      "date": "2017-08-27",
      "title": "初台theDOORS",
      "form": "BAND"
    },
    {
      "id": 134,
      "date": "2017-10-21",
      "title": "Only The FOXGOD Unknown",
      "form": "BAND"
    },
    {
      "id": 133,
      "date": "2018-01-28",
      "title": "DizzFEST vol.1",
      "form": "BAND"
    },
    {
      "id": 132,
      "date": "2018-04-22",
      "title": "DizzFEST vol.2",
      "form": "BAND"
    },
    {
      "id": 131,
      "date": "2018-07-01",
      "title": "DizzFEST vol.3",
      "form": "BAND"
    },
    {
      "id": 130,
      "date": "2018-12-09",
      "title": "\"THE ONE\" -man show-",
      "form": "BAND"
    }
  ]
}